estreamer
