Metadata-Version: 1.1
Name: estreamer
Version: 0.1.1
Summary: SourceFire eStream client Python library
Home-page: https://github.com/spohara79/estreamer/
Author: Sean O'Hara
Author-email: spohara@gmail.com
License: Apache Software License
Keywords: sample setuptools development
Platform: UNKNOWN
Classifier: Development Status :: 3 - Alpha
Classifier: Intended Audience :: Developers
Classifier: Natural Language :: English
Classifier: Topic :: Software Development :: Libraries :: Python Modules
Classifier: Programming Language :: Python
Classifier: Programming Language :: Python :: 2.7
